Metadata-Version: 2.1
Name: postgres-adm
Version: 1.0.2
Summary: PostgreSQL has the function of facilitating the use of methods for executing SQL statements.
Author: Ryan Souza Anselmo
Author-email: ryansouza.cwb@email.com
License: MIT License
Keywords: postgres-adm
License-File: LICENSE
Requires-Dist: psycopg2
